initcommerce/__init__.py
initcommerce/cache/__init__.py
initcommerce/cache/redis.py
initcommerce/common/__init__.py
initcommerce/common/entity.py
initcommerce/common/exceptions.py
initcommerce/common/jwt.py
initcommerce/common/logger.py
initcommerce/common/settings.py
initcommerce/common/utils.py
initcommerce/common/uuid.py
initcommerce/common/validators.py
initcommerce/common/value_object.py
initcommerce/common/webapi.py
initcommerce/database/__init__.py
initcommerce/database/sql.py
initcommerce/message_queue/__init__.py
initcommerce/message_queue/rabbitmq.py
initcommerce/notification/__init__.py
initcommerce/notification/email_sender.py
initcommerce/notification/sms_sender.py
initcommerce/object_storage/__init__.py
initcommerce/object_storage/minio.py
initcommerce/tests/__init__.py
initcommerce/tests/webapi.py
initcommerce_utils-1.4.0.dist-info/LICENSE
initcommerce_utils-1.4.0.dist-info/METADATA
initcommerce_utils-1.4.0.dist-info/WHEEL
initcommerce_utils-1.4.0.dist-info/top_level.txt
initcommerce_utils-1.4.0.dist-info/RECORD
